hackrf/__init__.py
hackrf/cinterface.py
hackrf/core.py
hackrf/scan.py
hackrf/utils.py
libhackrf-0.1a4.dist-info/LICENSE.md
libhackrf-0.1a4.dist-info/METADATA
libhackrf-0.1a4.dist-info/WHEEL
libhackrf-0.1a4.dist-info/top_level.txt
libhackrf-0.1a4.dist-info/RECORD
