Metadata-Version: 2.1
Name: libhackrf
Version: 0.1a4
Summary: A Python library for interfacing with HackRF software-defined radio hardware, enabling signal reception and transmission, frequency scanning, and data processing.
Author-email: Yeison Cardona <yencardonaal@unal.edu.co>
Maintainer-email: Yeison Cardona <yencardonaal@unal.edu.co>
License: BSD-2-Clause
Project-URL: Repository, https://github.com/dunderlab/python-libhackrf
Classifier: Development Status :: 3 - Alpha
Classifier: Environment :: Console
Classifier: Intended Audience :: Developers
Classifier: Intended Audience :: Science/Research
Classifier: License :: OSI Approved :: BSD License
Classifier: Natural Language :: English
Classifier: Operating System :: OS Independent
Classifier: Programming Language :: Python
Classifier: Programming Language :: Python :: 3.8
Classifier: Programming Language :: Python :: 3.9
Classifier: Programming Language :: Python :: 3.10
Classifier: Programming Language :: Python :: 3.11
Classifier: Programming Language :: Python :: 3.12
Classifier: Topic :: Software Development :: Libraries :: Python Modules
Requires-Python: >=3.8
License-File: LICENSE.md
Provides-Extra: dev
Requires-Dist: numpy; extra == "dev"
